pykebabs/__init__.py
pykebabs/__main__.py
pykebabs/pykebabsclass.py
pykebabs-1.0.1.dist-info/LICENSE
pykebabs-1.0.1.dist-info/METADATA
pykebabs-1.0.1.dist-info/WHEEL
pykebabs-1.0.1.dist-info/entry_points.txt
pykebabs-1.0.1.dist-info/top_level.txt
pykebabs-1.0.1.dist-info/RECORD
