Metadata-Version: 2.1
Name: pykebabs
Version: 1.0.1
Summary: Easy to use String Kernels for SVM
Author-email: florian-wagner <mindbrix@gmx.at>
License: MIT License        
Keywords: SVM,StringKernel,open
Classifier: License :: OSI Approved :: MIT License
Classifier: Programming Language :: Python
Requires-Python: >=3.8
License-File: LICENSE
Requires-Dist: pandas
Requires-Dist: numpy
Requires-Dist: matplotlib
Requires-Dist: sklearn
Requires-Dist: scipy
Requires-Dist: seaborn
Requires-Dist: Bio
Provides-Extra: dev
Requires-Dist: black ; extra == 'dev'
Requires-Dist: bumpver ; extra == 'dev'
Requires-Dist: isort ; extra == 'dev'
Requires-Dist: pip-tools ; extra == 'dev'
Requires-Dist: pytest ; extra == 'dev'
